mqttdebug/__init__.py
mqttdebug/mqttpublish.py
mqttdebug/mqttsubscribe.py
mqttdebug_tspspi-0.0.1a2.dist-info/LICENSE.md
mqttdebug_tspspi-0.0.1a2.dist-info/METADATA
mqttdebug_tspspi-0.0.1a2.dist-info/WHEEL
mqttdebug_tspspi-0.0.1a2.dist-info/entry_points.txt
mqttdebug_tspspi-0.0.1a2.dist-info/top_level.txt
mqttdebug_tspspi-0.0.1a2.dist-info/RECORD
