Metadata-Version: 2.1
Name: mqttdebug-tspspi
Version: 0.0.1a2
Summary: A simple MQTT debugging utility that allows subscribing to an arbitrary number of topics / publishing messages from the CLI
Home-page: https://github.com/tspspi/mqttdebug
Author: Thomas Spielauer
Author-email: pypipackages01@tspi.at
Classifier: Programming Language :: Python :: 3
Classifier: License :: OSI Approved :: BSD License
Classifier: Operating System :: OS Independent
Requires-Python: >=3.6
License-File: LICENSE.md
Requires-Dist: paho-mqtt >=1.6.1
Requires-Dist: numpy >=1.25
